flask_spyne/__init__.py
flask_spyne/flask_spyne.py
flask_spyne_py3-1.0.0.dist-info/METADATA
flask_spyne_py3-1.0.0.dist-info/WHEEL
flask_spyne_py3-1.0.0.dist-info/top_level.txt
flask_spyne_py3-1.0.0.dist-info/RECORD
