Metadata-Version: 2.1
Name: flask-spyne-py3
Version: 1.0.0
Summary: A Flask extension, provides support for Spyne.
Download-URL: http://pypi.python.org/pypi/flask-spyne-py3
Author: Alejo Sarmiento
Author-email: asarmiento@leafnoise.io
License: CC0 1.0
Keywords: flask,spyne,soap,wsdl,wsgi,zeromq,rest,rpc,json,http,msgpack,xml,werkzeug,yaml
Platform: any
Classifier: Development Status :: 4 - Beta
Classifier: Environment :: Web Environment
Classifier: Intended Audience :: Developers
Classifier: License :: CC0 1.0 Universal (CC0 1.0) Public Domain Dedication
Classifier: Operating System :: OS Independent
Classifier: Programming Language :: Python
Classifier: Topic :: Internet :: WWW/HTTP
Classifier: Topic :: Software Development :: Libraries :: Python Modules
Requires-Dist: flask
Requires-Dist: spyne
Requires-Dist: sec-wall-py3
Requires-Dist: pyyaml
Requires-Dist: lxml
Requires-Dist: suds-py3
Requires-Dist: requests
